{"teams":[{"idTeam":"136492","idSoccerXML":null,"idAPIfootball":"1516","intLoved":null,"strTeam":"Benin","strTeamShort":null,"strAlternate":"","intFormedYear":"1959","strSport":"Soccer","strLeague":"African Cup of Nations","idLeague":"4496","strDivision":null,"strManager":"","strStadium":"Stade de l'Amitié","strKeywords":"","strRSS":"","strStadiumThumb":null,"strStadiumDescription":"Stade de l'Amitie or Friendship Stadium is a multi-purpose stadium in Cotonou, Benin. It is currently used for football matches and also has facilities for athletics. The stadium has a capacity of 20,000 people.","strStadiumLocation":"","intStadiumCapacity":"20000","strWebsite":"","strFacebook":"","strTwitter":"","strInstagram":"","strDescriptionEN":"The Benin national football team, nicknamed Les Écureuils (The Squirrels), is the national football team of Benin and is controlled by the Benin Football Federation. They were known as the Dahomey national football team until 1975, when Republic of Dahomey became Benin. They have never qualified for the World Cup, but have reached three recent African Nations Cups – 2004, 2008, and 2010. On 8 February 2010 after the preliminary competition from the 2010 Africa Cup of Nations in Angola, the Benin Football Federation dissolved the national team, coach Henri Dussuyer and his complete staff were fired. On May 9, 2016, Benin was suspended from FIFA.","strDescriptionDE":null,"strDescriptionFR":null,"strDescriptionCN":null,"strDescriptionIT":null,"strDescriptionJP":null,"strDescriptionRU":null,"strDescriptionES":null,"strDescriptionPT":null,"strDescriptionSE":null,"strDescriptionNL":null,"strDescriptionHU":null,"strDescriptionNO":null,"strDescriptionIL":null,"strDescriptionPL":null,"strGender":"Male","strCountry":"International","strTeamBadge":"https:\/\/www.thesportsdb.com\/images\/media\/team\/badge\/ellcoi1553345873.png","strTeamJersey":null,"strTeamLogo":null,"strTeamFanart1":null,"strTeamFanart2":null,"strTeamFanart3":null,"strTeamFanart4":null,"strTeamBanner":null,"strYoutube":"","strLocked":"unlocked"}]}